{
  "appname": "PDFActions",
  "home_page": {
    "why_use": {
      "title": "Why Use",
      "reasons": [
        {
          "icon": "/icons/why_use/cost_free.png",
          "title": "Cost free convinience",
          "description": "Enjoy PDFActions for personal and business use without any charges or registration hassles."
        },
        {
          "icon": "/icons/why_use/security.png",
          "title": "Fortified security measures",
          "description": "Secure PDFActions: Browser based process ensures data confidentiality, preventing third- party access."
        },
        {
          "icon": "/icons/why_use/efficiency.png",
          "title": "Efficiency unleashed",
          "description": "Effortless PDF tasks in 3 steps, no extra software. PDFActions swiftly manages any size."
        },
        {
          "icon": "/icons/why_use/accessible.png",
          "title": "Universal accessibility",
          "description": "Web-based PDFActions: Cross-platform, seamless access from any computer, major browser support."
        }
      ]
    },
    "footer": {
      "top": {
        "about_us": "About Us",
        "about_us_text": "Welcome to PDFActions - your secure, hassle-free PDF solution. Process files in your browser with no data uploads. Works on Windows, Mac, Linux, and mobile devices. Simplify your PDF tasks with us!",
        "developers": [
          {
            "avatar": "/images/developers/manas.png",
            "name": "Manas Madan",
            "position": "Web Developer",
            "tagline": { "first": "Code Maestro,", "last": "Web Wizard" },
            "email": "manasmadan08@gmail.com",
            "social_links": [
              {
                "icon": "/icons/socials/github.png",
                "link": "https://www.github.com/ManasMadan"
              },
              {
                "icon": "/icons/socials/linkedin.png",
                "link": "https://www.linkedin.com/in/manas-madan/"
              },
              {
                "icon": "/icons/socials/website.png",
                "link": "https://linktr.ee/manasmadan"
              }
            ]
          },
          {
            "avatar": "/images/developers/ayush.png",
            "name": "Ayush Arora",
            "position": "UI/UX Designer",
            "tagline": { "first": "Design Dynamo,", "last": "Pixel Pioneer" },
            "email": "ayusharora4102004@gmail.com",
            "social_links": [
              {
                "icon": "/icons/socials/linkedin.png",
                "link": "https://www.linkedin.com/in/ayush-arora4/"
              },
              {
                "icon": "/icons/socials/dribbble.png",
                "link": "https://www.linkedin.com/in/ayush-arora4/"
              }
            ]
          }
        ],
        "powered_by": "Powered By"
      },
      "bottom": {
        "copyright_left": "Copyright ",
        "copyright_right": " - Delhi, Inc",
        "privacy_policy": "Privacy Policy"
      }
    }
  }
}
